[
  {
    "url": "/weibo?q=%23%E5%85%B1%E5%88%9B%E4%B8%AD%E9%9D%9E%E7%BE%8E%E5%A5%BD%E6%9C%AA%E6%9D%A5%23&Refer=new_time",
    "title": "共创中非美好未来"
  },
  {
    "url": "/weibo?q=%23%E9%83%91%E9%92%A6%E6%96%87%E6%97%A0%E7%BC%98%E7%BE%8E%E7%BD%914%E5%BC%BA%23&t=31&band_rank=1&Refer=top",
    "title": "郑钦文无缘美网4强"
  },
  {
    "url": "/weibo?q=%23%E6%9B%BE%E5%BF%97%E4%BC%9F%E8%BF%9E%E5%A4%9C%E6%94%B9%E5%90%8D%E5%8E%BB%E6%8E%89%E4%B8%89%E5%8F%AA%E7%BE%8A%23&t=31&band_rank=2&Refer=top",
    "title": "曾志伟连夜改名去掉三只羊"
  },
  {
    "url": "/weibo?q=%2390%E7%A7%92%E7%A7%91%E6%99%AE%E4%B8%AD%E9%9D%9E%E5%90%88%E4%BD%9C%E6%88%90%E6%9E%9C%23&t=31&band_rank=3&Refer=top",
    "title": "90秒科普中非合作成果"
  },
  {
    "url": "/weibo?q=%23%E4%B8%89%E5%8F%AA%E7%BE%8A%E5%A5%B3%E4%B8%BB%E6%92%AD%E6%B2%AB%E6%B2%AB%E5%B7%B2%E6%9C%899%E4%B8%AA%E6%9C%88%E6%9C%AA%E6%9B%B4%E6%96%B0%23&t=31&band_rank=4&Refer=top",
    "title": "三只羊女主播沫沫已有9个月未更新"
  },
  {
    "url": "/weibo?q=%23%E9%83%91%E9%92%A6%E6%96%87vs%E8%90%A8%E5%B7%B4%E4%BC%A6%E5%8D%A1%23&t=31&band_rank=5&Refer=top",
    "title": "郑钦文vs萨巴伦卡"
  },
  { "url": "/weibo?q=%23iPhone16%E5%AE%9A%E4%BB%B7%23&t=31&band_rank=6&Refer=top", "title": "iPhone16定价" },
  {
    "url": "/weibo?q=%23%E7%94%B7%E5%AD%A9%E5%BC%80%E5%AD%A6%E5%A4%B1%E8%81%94%E8%A2%AB%E5%8F%91%E7%8E%B0%E8%BA%B2%E5%A4%A7%E4%BC%AF%E5%AE%B6%E5%90%B9%E7%A9%BA%E8%B0%83%23&t=31&band_rank=7&Refer=top",
    "title": "男孩开学失联被发现躲大伯家吹空调"
  },
  {
    "url": "/weibo?q=%E8%BE%9B%E5%B7%B4%20%E4%B8%89%E5%8F%AA%E7%BE%8A&t=31&band_rank=8&Refer=top",
    "title": "辛巴 三只羊"
  },
  {
    "url": "/weibo?q=%E9%A2%9C%E6%80%A1%E9%A2%9C%E6%82%A6%20%E4%B8%83%E4%B8%AA%E7%9F%AE%E5%AD%90%E6%94%BE%E7%8E%B0%E5%9C%A8%E5%8F%AB%E7%94%B7%E5%9B%A2&t=31&band_rank=9&Refer=top",
    "title": "颜怡颜悦 七个矮子放现在叫男团"
  },
  {
    "url": "/weibo?q=%23%E9%AB%98%E9%93%81%E4%B8%8A%E4%B8%80%E5%AF%B9%E9%80%80%E5%BD%B9%E5%86%9B%E4%BA%BA%E6%83%85%E4%BE%A3%E7%81%AB%E4%BA%86%23&t=31&band_rank=10&Refer=top",
    "title": "高铁上一对退役军人情侣火了"
  },
  {
    "url": "/weibo?q=%23%E8%90%A8%E5%B7%B4%E4%BC%A6%E5%8D%A1%E5%A5%BD%E5%A3%AE%23&t=31&band_rank=11&Refer=top",
    "title": "萨巴伦卡好壮"
  },
  {
    "url": "/weibo?q=%E6%95%A3%E6%89%93%E5%93%A5%20%E8%BE%9B%E5%B7%B4%E8%AF%B4%E7%9A%84%E6%98%AF%E7%9C%9F%E7%9A%84&t=31&band_rank=12&Refer=top",
    "title": "散打哥 辛巴说的是真的"
  },
  {
    "url": "/weibo?q=%23%E7%8E%B0%E5%9C%A8%E5%B0%8F%E6%9C%8B%E5%8F%8B%E7%9A%84%E5%90%8D%E5%AD%97%E8%BF%99%E4%B9%88%E4%B8%BB%E8%A7%92%E6%84%9F%E7%9A%84%E4%B9%88%23&t=31&band_rank=13&Refer=top",
    "title": "现在小朋友的名字这么主角感的么"
  },
  { "url": "/weibo?q=%E4%B8%89%E5%8F%AA%E7%BE%8A&t=31&band_rank=14&Refer=top", "title": "三只羊" },
  {
    "url": "/weibo?q=%23%E9%83%91%E9%92%A6%E6%96%87%E4%B8%8D%E6%95%8C%E8%90%A8%E5%B7%B4%E4%BC%A6%E5%8D%A1%23&t=31&band_rank=15&Refer=top",
    "title": "郑钦文不敌萨巴伦卡"
  },
  {
    "url": "/weibo?q=%23%E5%BC%A0%E9%9B%A8%E9%9C%8F%E8%AF%B4%E4%B8%80%E4%B8%AA%E6%9C%88%E6%B2%A1%E4%B8%8B%E6%B0%B4%E7%97%9B%E7%BB%8F%E5%A5%BD%E5%BE%88%E5%A4%9A%23&t=31&band_rank=16&Refer=top",
    "title": "张雨霏说一个月没下水痛经好很多"
  },
  {
    "url": "/weibo?q=%23%E7%94%B5%E9%B8%A1%E4%B8%80%E5%B9%B4%E5%8D%81%E6%AC%A1%E4%BB%A5%E4%B8%8A%E5%A4%84%E7%BD%9A%E6%88%96%E5%BD%B1%E5%93%8D%E5%BE%81%E4%BF%A1%23&t=31&band_rank=17&Refer=top",
    "title": "电鸡一年十次以上处罚或影响征信"
  },
  {
    "url": "/weibo?q=%E6%9D%A8%E7%AC%A0%20%E8%BF%99%E6%98%AF%E8%A1%80%E8%82%89%E5%9C%A8%E7%96%AF%E9%95%BF%E7%9A%84%E5%A3%B0%E9%9F%B3&t=31&band_rank=18&Refer=top",
    "title": "杨笠 这是血肉在疯长的声音"
  },
  {
    "url": "/weibo?q=%23%E8%B5%B5%E9%9C%B2%E6%80%9D%E7%8E%A9%E7%94%84%E5%AC%9B%E4%BC%A0%E6%A2%97%23&t=31&band_rank=19&Refer=top",
    "title": "赵露思玩甄嬛传梗"
  },
  {
    "url": "/weibo?q=%E8%BF%99%E5%B1%85%E7%84%B6%E6%98%AF%E7%A7%A6%E4%BF%8A%E6%9D%B0&t=31&band_rank=20&Refer=top",
    "title": "这居然是秦俊杰"
  },
  {
    "url": "/weibo?q=%2340%E5%B2%81%E4%BB%A5%E4%B8%8A%E5%A5%B3%E6%80%A7%E7%A6%81%E7%94%A8%E7%B4%A7%E6%80%A5%E9%81%BF%E5%AD%95%E8%8D%AF%23&t=31&band_rank=21&Refer=top",
    "title": "40岁以上女性禁用紧急避孕药"
  },
  {
    "url": "/weibo?q=%E5%A4%A7%E5%AE%B6%E5%B7%A5%E4%BD%9C%E4%B8%80%E5%AE%9A%E8%A6%81%E5%AF%B9%E5%B7%A5%E8%B5%84%E6%9C%89%E6%A6%82%E5%BF%B5&t=31&band_rank=22&Refer=top",
    "title": "大家工作一定要对工资有概念"
  },
  {
    "url": "/weibo?q=%23%E7%94%B7%E5%AD%A9%E9%AA%91%E8%A1%8C%E9%81%AD%E7%A2%BE%E5%8E%8B%E8%BA%AB%E4%BA%A1%E5%8F%B8%E6%9C%BA%E5%A6%BB%E5%AD%90%E6%82%A3%E7%99%BD%E8%A1%80%E7%97%85%23&t=31&band_rank=23&Refer=top",
    "title": "男孩骑行遭碾压身亡司机妻子患白血病"
  },
  { "url": "/weibo?q=%E7%8C%AB%20%E9%82%A3%E5%92%8B%E4%BA%86&t=31&band_rank=24&Refer=top", "title": "猫 那咋了" },
  {
    "url": "/weibo?q=%23%E5%84%BF%E7%AB%A5%E9%AA%91%E8%A1%8C%E8%A2%AB%E7%A2%BE%E5%8E%8B%E6%A1%88%E5%8F%B8%E6%9C%BA%E4%BA%B2%E5%B1%9E%E5%8F%91%E5%A3%B0%23&t=31&band_rank=25&Refer=top",
    "title": "儿童骑行被碾压案司机亲属发声"
  },
  {
    "url": "/weibo?q=%23%E7%A2%BE%E5%8E%8B%E9%AA%91%E8%A1%8C%E7%94%B7%E5%AD%A9%E6%B6%89%E6%A1%88%E5%8F%B8%E6%9C%BA%E5%BE%8B%E5%B8%88%E5%8F%91%E5%A3%B0%23&t=31&band_rank=26&Refer=top",
    "title": "碾压骑行男孩涉案司机律师发声"
  },
  {
    "url": "/weibo?q=%23%E8%A2%AB%E6%89%93%E7%94%B7%E5%8F%B8%E6%9C%BA%E6%8C%A8%E6%89%93%E8%BF%98%E6%89%8B%E7%AE%97%E6%AD%A3%E5%BD%93%E9%98%B2%E5%8D%AB%E5%90%97%23&t=31&band_rank=27&Refer=top",
    "title": "被打男司机挨打还手算正当防卫吗"
  },
  {
    "url": "/weibo?q=%23%E9%9D%92%E5%B2%9B%E8%AD%A6%E6%96%B9%E9%80%9A%E6%8A%A5%E7%8E%8B%E6%9F%90%E9%A9%BE%E8%BD%A6%E9%80%86%E8%A1%8C%E6%AE%B4%E6%89%93%E4%BB%96%E4%BA%BA%E6%A1%88%23&t=31&band_rank=28&Refer=top",
    "title": "青岛警方通报王某驾车逆行殴打他人案"
  },
  {
    "url": "/weibo?q=%23%E9%98%9A%E6%B8%85%E5%AD%90%E8%AF%B4%E6%81%8B%E7%88%B1%E8%B0%88%E5%A4%AA%E5%A4%9A%E4%B9%9F%E4%B8%8D%E5%A5%BD%23&t=31&band_rank=29&Refer=top",
    "title": "阚清子说恋爱谈太多也不好"
  },
  {
    "url": "/weibo?q=%23%E7%BF%81%E9%9D%92%E9%9B%85%E5%BD%AD%E9%AB%98%E5%A5%BD%E5%97%91%23&t=31&band_rank=30&Refer=top",
    "title": "翁青雅彭高好嗑"
  },
  {
    "url": "/weibo?q=%23%E9%83%91%E9%92%A6%E6%96%87%E7%BE%8E%E7%BD%91%E6%94%B6%E8%8E%B7430%E7%A7%AF%E5%88%86375%E4%B8%87%E5%A5%96%E9%87%91%23&t=31&band_rank=31&Refer=top",
    "title": "郑钦文美网收获430积分375万奖金"
  },
  {
    "url": "/weibo?q=%23024596%E8%AD%A6%E5%8F%B7%E9%87%8D%E5%90%AF%23&t=31&band_rank=32&Refer=top",
    "title": "024596警号重启"
  },
  {
    "url": "/weibo?q=%23%E5%8E%9F%E6%9D%A5%E8%BF%99%E4%BA%9B%E9%83%BD%E6%98%AF%E5%81%87%E7%89%9B%E8%82%89%23&t=31&band_rank=33&Refer=top",
    "title": "原来这些都是假牛肉"
  },
  {
    "url": "/weibo?q=%23%E6%88%B4%E5%BB%BA%E4%B8%9A%E8%AF%B435%E5%B2%81%E5%A4%B1%E4%B8%9A%E8%AE%A9%E4%BA%BA%E4%BB%AC%E4%B8%8D%E6%95%A2%E7%94%9F%E8%82%B2%23&t=31&band_rank=34&Refer=top",
    "title": "戴建业说35岁失业让人们不敢生育"
  },
  {
    "url": "/weibo?q=%E9%80%A0%E5%9E%8B%E5%B8%88%E6%8A%8A%E5%BC%A0%E9%9F%B6%E6%B6%B5%E5%BD%93%E6%B4%8B%E5%A8%83%E5%A8%83%E5%85%BB&t=31&band_rank=35&Refer=top",
    "title": "造型师把张韶涵当洋娃娃养"
  },
  {
    "url": "/weibo?q=%E6%B2%88%E8%85%BE%E4%B8%80%E4%B8%AA%E6%B8%B8%E6%88%8F%E5%BE%97%E7%BD%AA%E9%A9%AC%E4%B8%BD%E8%8C%83%E4%B8%9E%E4%B8%9E%E8%B4%BE%E7%8E%B2&t=31&band_rank=36&Refer=top",
    "title": "沈腾一个游戏得罪马丽范丞丞贾玲"
  },
  {
    "url": "/weibo?q=%23%E5%8D%AB%E5%81%A5%E5%B1%80%E5%9B%9E%E5%BA%94%E7%94%B7%E5%AD%901%E5%A4%A9%E6%8B%9423%E9%A2%97%E7%89%99%E5%90%8E%E5%8E%BB%E4%B8%96%23&t=31&band_rank=37&Refer=top",
    "title": "卫健局回应男子1天拔23颗牙后去世"
  },
  {
    "url": "/weibo?q=%23%E5%8C%97%E6%96%B9%E5%A4%9A%E5%9C%B0%E4%B8%80%E9%9B%A8%E6%88%90%E7%A7%8B%E5%8D%97%E6%96%B9%E6%9A%91%E7%83%AD%E4%BE%9D%E6%97%A7%23&t=31&band_rank=38&Refer=top",
    "title": "北方多地一雨成秋南方暑热依旧"
  },
  {
    "url": "/weibo?q=%23%E8%B4%B9%E5%BE%B7%E5%8B%92%E8%A7%82%E6%88%98%E9%83%91%E9%92%A6%E6%96%87%23&t=31&band_rank=39&Refer=top",
    "title": "费德勒观战郑钦文"
  },
  {
    "url": "/weibo?q=%23%E8%AD%A6%E6%96%B9%E5%9B%9E%E5%BA%94%E5%8D%9A%E4%B8%BB%E6%8C%91%E6%88%98%E9%B3%8C%E5%A4%AA%E7%BA%BF%E5%8F%91%E7%8E%B0%E7%94%B7%E5%B0%B8%23&t=31&band_rank=40&Refer=top",
    "title": "警方回应博主挑战鳌太线发现男尸"
  },
  {
    "url": "/weibo?q=%23%E6%B2%B3%E5%8D%97%E4%B8%AD%E7%89%9F%E9%80%9A%E6%8A%A5%E6%95%99%E5%AE%98%E4%BD%93%E7%BD%9A14%E5%B2%81%E5%A5%B3%E7%94%9F%23&t=31&band_rank=41&Refer=top",
    "title": "河南中牟通报教官体罚14岁女生"
  },
  {
    "url": "/weibo?q=%23%E5%A4%A9%E6%B4%A52%E4%B9%A6%E5%BA%97%E5%A4%96%E5%AE%B6%E9%95%BF%E5%A4%9C%E6%99%9A%E6%8E%92%E9%95%BF%E9%98%9F%E4%B9%B0%E4%B9%A6%23&t=31&band_rank=42&Refer=top",
    "title": "天津2书店外家长夜晚排长队买书"
  },
  {
    "url": "/weibo?q=%E7%9B%9B%E6%9D%8E%E8%B1%AA%20%E5%AD%A4%E5%8B%87%E8%80%85%E7%89%88&t=31&band_rank=43&Refer=top",
    "title": "盛李豪 孤勇者版"
  },
  {
    "url": "/weibo?q=%E7%AA%81%E7%84%B6%E4%BB%8E%E9%80%80%E4%BC%8D%E6%8E%A5%E7%AB%99%E5%8F%98%E6%88%90%E4%BA%86%E7%88%B1%E8%B1%86%E6%8E%A5%E6%9C%BA&t=31&band_rank=44&Refer=top",
    "title": "突然从退伍接站变成了爱豆接机"
  },
  {
    "url": "/weibo?q=%23%E9%83%91%E9%92%A6%E6%96%87%E5%8F%91%E7%90%83%E7%AB%99%E4%BD%8D%23&t=31&band_rank=45&Refer=top",
    "title": "郑钦文发球站位"
  },
  {
    "url": "/weibo?q=%23%E9%83%91%E9%92%A6%E6%96%87%E4%BB%8A%E5%B9%B4%E5%A4%A7%E6%BB%A1%E8%B4%AF%E6%88%90%E7%BB%A9%23&t=31&band_rank=46&Refer=top",
    "title": "郑钦文今年大满贯成绩"
  },
  {
    "url": "/weibo?q=%E5%A6%88%E5%A6%88%E6%AF%94%E6%AD%BB%E7%A5%9E%E5%85%88%E5%88%B0%E4%B8%80%E6%AD%A5&t=31&band_rank=47&Refer=top",
    "title": "妈妈比死神先到一步"
  },
  {
    "url": "/weibo?q=%23%E4%B8%8A%E6%B5%B7%E5%AF%B9%E7%AC%A6%E5%90%88%E8%A6%81%E6%B1%82%E5%AE%B6%E5%B1%85%E5%AE%B6%E7%94%B5%E6%B6%88%E8%B4%B9%E8%A1%A5%E8%B4%B415%25%23&t=31&band_rank=48&Refer=top",
    "title": "上海对符合要求家居家电消费补贴15%"
  },
  {
    "url": "/weibo?q=%23%E7%A2%BE%E5%8E%8B%E9%AA%91%E8%A1%8C%E5%AD%A9%E7%AB%A5%E5%8F%B8%E6%9C%BA%E4%BB%A5%E8%BF%87%E5%A4%B1%E8%87%B4%E6%AD%BB%E7%BD%AA%E8%A2%AB%E6%8D%95%23&t=31&band_rank=49&Refer=top",
    "title": "碾压骑行孩童司机以过失致死罪被捕"
  },
  {
    "url": "/weibo?q=%2312306%E5%9B%9E%E5%BA%9429%E5%85%83%E5%9D%90%E9%AB%98%E9%93%81%E5%85%8D%E8%B4%B9%E5%90%8340%E5%85%83%E7%9B%92%E9%A5%AD%23&t=31&band_rank=50&Refer=top",
    "title": "12306回应29元坐高铁免费吃40元盒饭"
  }
]
